_jopus_cython.cpython-37m-x86_64-linux-gnu.so
.libs_jopus_cython/libkeyutils-dfe70bd6.so.1.5
.libs_jopus_cython/libkrb5-c4b42758.so.3.3
.libs_jopus_cython/libopusfile-a90fc0fd.so.0.3.0
.libs_jopus_cython/libgssapi_krb5-92a3b421.so.2.2
.libs_jopus_cython/libk5crypto-99d9cebb.so.3.1
.libs_jopus_cython/libopus-abf1ee53.so.0.3.0
.libs_jopus_cython/libpcre-9513aab5.so.1.2.0
.libs_jopus_cython/libcrypto-957ef781.so.1.0.2k
.libs_jopus_cython/libopusurl-e756f25d.so.0.3.0
.libs_jopus_cython/libz-d8a329de.so.1.2.7
.libs_jopus_cython/libogg-24eaa32b.so.0.8.0
.libs_jopus_cython/libselinux-8db37e25.so.1
.libs_jopus_cython/libkrb5support-f5716915.so.0.1
.libs_jopus_cython/libssl-84c8c57b.so.1.0.2k
.libs_jopus_cython/libcom_err-20a7370a.so.2.1
jopus/__init__.py
jopus-0.0.2.dist-info/METADATA
jopus-0.0.2.dist-info/RECORD
jopus-0.0.2.dist-info/top_level.txt
jopus-0.0.2.dist-info/WHEEL
jopus-0.0.2.dist-info/zip-safe
