Metadata-Version: 2.1
Name: jopus
Version: 0.0.2
Summary: Simple Python wrapper for libopusfile
Home-page: https://github.com/yutkin/jopus
Author: Dmitry Yutkin
License: MIT
Platform: UNKNOWN
Classifier: License :: OSI Approved :: MIT License
Classifier: Programming Language :: Python
Classifier: Programming Language :: Python :: 3
Classifier: Programming Language :: Python :: 3.6
Classifier: Programming Language :: Python :: 3.7
Classifier: Programming Language :: Python :: 3.8
Classifier: Programming Language :: Python :: Implementation :: CPython
Classifier: Programming Language :: Cython
Classifier: Programming Language :: C
Classifier: Programming Language :: C++
Requires-Python: >=3.6.0
Requires-Dist: numpy
